py_smsgateway_async-0.1.2.dist-info/licenses/LICENSE
sms_gateway/__init__.py
sms_gateway/__main__.py
sms_gateway/api.py
sms_gateway/app.py
sms_gateway/config.py
sms_gateway/gateway.py
py_smsgateway_async-0.1.2.dist-info/METADATA
py_smsgateway_async-0.1.2.dist-info/WHEEL
py_smsgateway_async-0.1.2.dist-info/entry_points.txt
py_smsgateway_async-0.1.2.dist-info/top_level.txt
py_smsgateway_async-0.1.2.dist-info/RECORD
