Metadata-Version: 2.4
Name: py-smsgateway-async
Version: 0.1.2
Summary: Asynchronous SMS gateway using Gammu with RESTful API interface
Author-email: Oscar Calvo <oscar@calvonet.com>
License-Expression: MIT
Keywords: sms,gammu,async,gateway,REST,modem
Requires-Python: >=3.7
License-File: LICENSE
Requires-Dist: aiohttp>=3.8
Requires-Dist: python-gammu
Dynamic: license-file
